git_authorship/__init__.py
git_authorship/__main__.py
git_authorship/_pathutils.py
git_authorship/_types.py
git_authorship/authorship.py
git_authorship/cli.py
git_authorship/config.py
git_authorship/exceptions.py
git_authorship/export.py
git_authorship-0.5.1.dist-info/LICENSE
git_authorship-0.5.1.dist-info/METADATA
git_authorship-0.5.1.dist-info/WHEEL
git_authorship-0.5.1.dist-info/entry_points.txt
git_authorship-0.5.1.dist-info/RECORD
