Metadata-Version: 2.1
Name: git-authorship
Version: 0.5.1
Summary: Interactive reports showing who wrote each line of code in your git repository.
Home-page: https://github.com/thehale/git-authorship
License: MPL-2.0
Keywords: git,blame,authorship,copyright,relicensing,SPDX,SBOM
Author: Joseph Hale
Author-email: me@jhale.dev
Requires-Python: >=3.8,<4.0
Classifier: License :: OSI Approved
Classifier: Programming Language :: Python :: 3
Classifier: Programming Language :: Python :: 3.8
Classifier: Programming Language :: Python :: 3.9
Classifier: Programming Language :: Python :: 3.10
Classifier: Programming Language :: Python :: 3.11
Classifier: Programming Language :: Python :: 3.12
Classifier: Programming Language :: Python :: 3.13
Requires-Dist: GitPython (>=3.1.43,<4.0.0)
Requires-Dist: plotly (>=5.24.1,<7.0.0)
Requires-Dist: typing-extensions (>=4.12.2,<5.0.0)
Project-URL: Documentation, https://github.com/thehale/git-authorship
Project-URL: Repository, https://github.com/thehale/git-authorship
